terminal_menu/__init__.py
terminal_menu/common.py
terminal_menu_interface-0.1.4.dist-info/METADATA
terminal_menu_interface-0.1.4.dist-info/WHEEL
terminal_menu_interface-0.1.4.dist-info/top_level.txt
terminal_menu_interface-0.1.4.dist-info/RECORD
