Metadata-Version: 2.1
Name: terminal-menu-interface
Version: 0.1.4
Summary: Esse pacote tem como função, democratizar a criação de menu em seus fluxos de código
Home-page: https://github.com/Augusto-cmk/Menu
Author: Augusto-cmk
Author-email: pedroaugustoms14@gmail.com
Classifier: Programming Language :: Python :: 3
Requires-Dist: readchar ==4.2.0
Requires-Dist: tabulate ==0.9.0
